setup.py
jsoncheck/__init__.py
jsoncheck.egg-info/PKG-INFO
jsoncheck.egg-info/SOURCES.txt
jsoncheck.egg-info/dependency_links.txt
jsoncheck.egg-info/not-zip-safe
jsoncheck.egg-info/top_level.txt