Metadata-Version: 1.0
Name: jsoncheck
Version: 1.0.1
Summary: python json schema validator with decent error messages
Home-page: https://github.com/rflynn/jsoncheck
Author: Ryan Flynn
Author-email: parseerror+github@gmail.com
License: MIT
Platform: UNKNOWN
